autoprompt/__init__.py
autoprompt/app.py
autoprompt-1.0.3.dist-info/METADATA
autoprompt-1.0.3.dist-info/WHEEL
autoprompt-1.0.3.dist-info/top_level.txt
autoprompt-1.0.3.dist-info/RECORD
