Metadata-Version: 2.1
Name: autoprompt
Version: 1.0.3
Summary: A short description of your package
Author: Biswanath Das
Author-email: cv.biswanath@gmail.com
Requires-Dist: env
